django_db_call/caller.py
django_db_call/__init__.py
django_db_call-0.2.0.dist-info/WHEEL
django_db_call-0.2.0.dist-info/RECORD
django_db_call-0.2.0.dist-info/DESCRIPTION.rst
django_db_call-0.2.0.dist-info/METADATA
django_db_call-0.2.0.dist-info/top_level.txt
django_db_call-0.2.0.dist-info/pydist.json
